HummingbirdDualMotorDriver.py
hummingbird_dual_motor_driver.py
hummingbird_dual_motor_driver/__init__.py
hummingbird_dual_motor_driver/__main__.py
hummingbird_dual_motor_driver/cli.py
hummingbird_dual_motor_driver-0.0.5.dist-info/AUTHORS.rst
hummingbird_dual_motor_driver-0.0.5.dist-info/LICENSE
hummingbird_dual_motor_driver-0.0.5.dist-info/METADATA
hummingbird_dual_motor_driver-0.0.5.dist-info/WHEEL
hummingbird_dual_motor_driver-0.0.5.dist-info/entry_points.txt
hummingbird_dual_motor_driver-0.0.5.dist-info/top_level.txt
hummingbird_dual_motor_driver-0.0.5.dist-info/RECORD
