Metadata-Version: 2.1
Name: hummingbird-dual-motor-driver
Version: 0.0.5
Summary: A dual motor driver for Birdbrain Technologies Hummingbird
Home-page: https://github.com/fmorton/hummingbird-dual-motor-driver
Author: Frank Morton
Author-email: fmorton@mac.com
License: MIT
Project-URL: Documentation, https://hummingbird-dual-motor-driver.readthedocs.io/
Project-URL: Changelog, https://hummingbird-dual-motor-driver.readthedocs.io/en/latest/changelog.html
Project-URL: Issue Tracker, https://github.com/fmorton/hummingbird-dual-motor-driver/issues
Classifier: Development Status :: 5 - Production/Stable
Classifier: Intended Audience :: Developers
Classifier: License :: OSI Approved :: MIT License
Classifier: Operating System :: Unix
Classifier: Operating System :: POSIX
Classifier: Operating System :: Microsoft :: Windows
Classifier: Programming Language :: Python
Classifier: Programming Language :: Python :: 3
Classifier: Programming Language :: Python :: 3 :: Only
Classifier: Programming Language :: Python :: 3.7
Classifier: Programming Language :: Python :: 3.8
Classifier: Programming Language :: Python :: 3.9
Classifier: Programming Language :: Python :: 3.10
Classifier: Programming Language :: Python :: Implementation :: CPython
Classifier: Programming Language :: Python :: Implementation :: PyPy
Classifier: Topic :: Utilities
Requires-Python: >=3.7
License-File: LICENSE
License-File: AUTHORS.rst
